<annotation>
    <folder>GE</folder>
    <filename>GE_19.jpg</filename>
    <size>
        <width>828</width>
        <height>750</height>
        <depth>3</depth>
    </size>
    <segmented>0</segmented>
    <object>
        <name>boat</name>
        <pose>Unspecified</pose>
        <truncated>0</truncated>
        <occluded>0</occluded>
        <difficult>0</difficult>
        <bndbox>
            <xmin>657</xmin>
            <ymin>512</ymin>
            <xmax>757</xmax>
            <ymax>683</ymax>
        </bndbox>
    </object>
    <object>
        <name>boat</name>
        <pose>Unspecified</pose>
        <truncated>0</truncated>
        <occluded>0</occluded>
        <difficult>0</difficult>
        <bndbox>
            <xmin>265</xmin>
            <ymin>215</ymin>
            <xmax>337</xmax>
            <ymax>340</ymax>
        </bndbox>
    </object>
</annotation>